Metadata-Version: 2.1
Name: meta-sparse
Version: 0.1.12
Summary: SPARSE indexes reference genomes in public databases into hierarchical clusters and uses it to predict origins of metagenomic reads.
Home-page: https://github.com/zheminzhou/SPARSE/
Author: Zhemin Zhou
Author-email: zhemin.zhou@warwick.ac.uk
License: UNKNOWN
Project-URL: Source, https://github.com/zheminzhou/SPARSE/
Project-URL: Bug Reports, https://github.com/zheminzhou/SPARSE/issues
Keywords: bioinformatics,microbial,metagenomics
Platform: UNKNOWN
Classifier: Development Status :: 5 - Production/Stable
Classifier: License :: OSI Approved :: GNU General Public License v3 (GPLv3)
Classifier: Programming Language :: Python :: 2
Classifier: Programming Language :: Python :: 2.7
